pycode128/__init__.py
pycode128/cli_tools/__init__.py
pycode128/cli_tools/cli.py
pycode128/code128_image.py
pycode128/py.typed
pycode128/py.typed.license
pycode128/pycode128.c
pycode128/pycode128.cpython-310-x86_64-linux-gnu.so
pycode128-3.0.0.dist-info/LICENSES/MIT.txt
pycode128-3.0.0.dist-info/METADATA
pycode128-3.0.0.dist-info/WHEEL
pycode128-3.0.0.dist-info/entry_points.txt
pycode128-3.0.0.dist-info/RECORD
