Metadata-Version: 2.1
Name: pycode128
Version: 3.0.0
Summary: Python extension for Code128 barcode generator library.
Home-page: https://github.com/gpongelli/pycode128
License: MIT
Author: Gabriele Pongelli
Author-email: gabriele.pongelli@gmail.com
Requires-Python: >=3.8.0,<4.0
Classifier: Development Status :: 5 - Production/Stable
Classifier: Intended Audience :: Developers
Classifier: License :: OSI Approved :: MIT License
Classifier: Natural Language :: English
Classifier: Programming Language :: Python :: 3
Classifier: Programming Language :: Python :: 3.8
Classifier: Programming Language :: Python :: 3.9
Classifier: Programming Language :: Python :: 3.10
Classifier: Programming Language :: Python :: 3.11
Classifier: Programming Language :: Python :: 3
Classifier: Programming Language :: Python :: 3.10
Classifier: Programming Language :: Python :: 3.11
Classifier: Programming Language :: Python :: 3.8
Classifier: Programming Language :: Python :: 3.9
Requires-Dist: click (==8.1.3)
Requires-Dist: cloup (>=2.0.0,<3.0.0)
Requires-Dist: pillow (>=9.4.0,<10.0.0)
Project-URL: Changelog, https://gpongelli.github.io/pycode128/history.html
Project-URL: Documentation, https://gpongelli.github.io/pycode128/
Project-URL: Issue Tracker, https://github.com/gpongelli/pycode128/issues
Project-URL: Source, https://github.com/gpongelli/pycode128
